oidc_rp/__init__.py
oidc_rp/admin.py
oidc_rp/apps.py
oidc_rp/backends.py
oidc_rp/context_processors.py
oidc_rp/middleware.py
oidc_rp/models.py
oidc_rp/signals.py
oidc_rp/urls.py
oidc_rp/utils.py
oidc_rp/views.py
oidc_rp/conf/__init__.py
oidc_rp/conf/settings.py
oidc_rp/contrib/__init__.py
oidc_rp/contrib/rest_framework/__init__.py
oidc_rp/contrib/rest_framework/authentication.py
oidc_rp/migrations/0001_initial.py
oidc_rp/migrations/__init__.py
django_oidc_rp-0.3.4.dist-info/LICENSE
django_oidc_rp-0.3.4.dist-info/METADATA
django_oidc_rp-0.3.4.dist-info/WHEEL
django_oidc_rp-0.3.4.dist-info/top_level.txt
django_oidc_rp-0.3.4.dist-info/RECORD
