Metadata-Version: 1.1
Name: django-oidc-rp
Version: 0.3.4
Summary: A server side OpenID Connect Relying Party (RP/Client) implementation for Django.
Home-page: https://github.com/impak-finance/django-oidc-rp
Author: impak Finance
Author-email: tech@impakfinance.com
License: MIT
Keywords: django openidconnect oidc client rp authentication auth
Platform: UNKNOWN
Classifier: Development Status :: 4 - Beta
Classifier: Environment :: Web Environment
Classifier: Framework :: Django
Classifier: Intended Audience :: Developers
Classifier: License :: OSI Approved :: MIT License
Classifier: Natural Language :: English
Classifier: Programming Language :: Python
Classifier: Programming Language :: Python :: 3
Classifier: Programming Language :: Python :: 3.4
Classifier: Programming Language :: Python :: 3.5
Classifier: Programming Language :: Python :: 3.6
Classifier: Programming Language :: Python :: 3.7
